sICTA/__init__.py
sICTA/customized_linear.py
sICTA/main.py
sICTA/pre.py
sICTA/sICTA_model.py
sICTA/train.py
sICTA-1.0.2.dist-info/LICENSE.txt
sICTA-1.0.2.dist-info/METADATA
sICTA-1.0.2.dist-info/WHEEL
sICTA-1.0.2.dist-info/top_level.txt
sICTA-1.0.2.dist-info/RECORD
