Metadata-Version: 2.1
Name: sICTA
Version: 1.0.2
Summary: A marker-based cell type annotation method that combines the self-training strategy with pseudo-labeling and the nonlinear association capturing capability of Transformer.
Home-page: https://github.com/nbnbhwyy/sICTA
Author: chg
Author-email: chenhg25@mail2.sysu.edu.cn
Classifier: Programming Language :: Python :: 3
Classifier: License :: OSI Approved :: MIT License
Classifier: Operating System :: OS Independent
Requires-Python: >=3.8
License-File: LICENSE.txt
